<?xml version="1.0" encoding="UTF-8"?>
<UserIntentions mediaName="CODE\win_b64\ENOVIA_SXI.media" mediaVersion="426">
  <SetVariable name="FullCloud_URL" value="http://dsplm24x.jxjty.com:19000"/>
  <SetVariable name="FullCloud_NumSlices" value="1"/>
  <SetVariable name="FullCloud_NumAnalyzers" value="8"/>
  <SetVariableProtected name="FullCloud_AdminPassword" value="Put your password here."/>
  <SetVariable item="NonHACloudview" name="Radio_InstallMODE" value="true"/>
  <SetVariable name="PATH_CVDATADIR_CUSTO" value="D:\DassaultSystemes\R2024x\3DSpaceIndex\win_b64\cv\data"/>
  <SetVariable item="Custom" name="Radio_mode" value="true"/>
  <SetVariable name="DSYWelcomePanel"/>
  <SetVariable name="TARGET_PATH" value="D:\DassaultSystemes\R2024x\3DSpaceIndex"/>
  <SetVariable name="FinishPanel"/>
</UserIntentions>